streamlit_image_select/__init__.py
streamlit_image_select/frontend/.env
streamlit_image_select/frontend/.prettierrc
streamlit_image_select/frontend/build/asset-manifest.json
streamlit_image_select/frontend/build/index.html
streamlit_image_select/frontend/build/precache-manifest.a32178d2b72e1f119edc27d01ed4cd8b.js
streamlit_image_select/frontend/build/service-worker.js
streamlit_image_select/frontend/build/static/js/2.e8544d91.chunk.js
streamlit_image_select/frontend/build/static/js/2.e8544d91.chunk.js.LICENSE.txt
streamlit_image_select/frontend/build/static/js/2.e8544d91.chunk.js.map
streamlit_image_select/frontend/build/static/js/main.4ff0b289.chunk.js
streamlit_image_select/frontend/build/static/js/main.4ff0b289.chunk.js.map
streamlit_image_select/frontend/build/static/js/runtime-main.fce4c018.js
streamlit_image_select/frontend/build/static/js/runtime-main.fce4c018.js.map
streamlit_image_select/frontend/build/styles.css
streamlit_image_select/frontend/package-lock.json
streamlit_image_select/frontend/package.json
streamlit_image_select/frontend/public/index.html
streamlit_image_select/frontend/public/styles.css
streamlit_image_select/frontend/src/index.tsx
streamlit_image_select/frontend/src/react-app-env.d.ts
streamlit_image_select/frontend/tsconfig.json
streamlit_image_select-0.4.0.dist-info/LICENSE
streamlit_image_select-0.4.0.dist-info/WHEEL
streamlit_image_select-0.4.0.dist-info/METADATA
streamlit_image_select-0.4.0.dist-info/RECORD
