Metadata-Version: 2.1
Name: streamlit-image-select
Version: 0.4.0
Summary: 🖼️ An image select component for Streamlit
License: MIT
Author: Johannes Rieke
Author-email: johannes.rieke@gmail.com
Requires-Python: >=3.8,<4.0
Classifier: License :: OSI Approved :: MIT License
Classifier: Programming Language :: Python :: 3
Classifier: Programming Language :: Python :: 3.10
Classifier: Programming Language :: Python :: 3.8
Classifier: Programming Language :: Python :: 3.9
Requires-Dist: streamlit (>=1.12.0,<2.0.0)
